datazen/__init__.py
datazen/__main__.py
datazen/app.py
datazen/compile.py
datazen/configs.py
datazen/dev_requirements.txt
datazen/entry.py
datazen/fingerprinting.py
datazen/load.py
datazen/parsing.py
datazen/paths.py
datazen/py.typed
datazen/requirements.txt
datazen/schemas.py
datazen/targets.py
datazen/templates.py
datazen/variables.py
datazen/classes/__init__.py
datazen/classes/data_repository.py
datazen/classes/file_info_cache.py
datazen/classes/target_resolver.py
datazen/classes/task_data_cache.py
datazen/classes/valid_dict.py
datazen/commands/__init__.py
datazen/commands/compile.py
datazen/commands/render.py
datazen/data/schema_types/deps.yaml
datazen/data/schema_types/paths.yaml
datazen/data/schemas/manifest.yaml
datazen/enums/__init__.py
datazen/environment/__init__.py
datazen/environment/base.py
datazen/environment/command.py
datazen/environment/compile.py
datazen/environment/config.py
datazen/environment/group.py
datazen/environment/integrated.py
datazen/environment/manifest.py
datazen/environment/manifest_cache.py
datazen/environment/render.py
datazen/environment/schema.py
datazen/environment/task.py
datazen/environment/template.py
datazen/environment/variable.py
datazen-3.2.3.dist-info/licenses/LICENSE
datazen-3.2.3.dist-info/METADATA
datazen-3.2.3.dist-info/WHEEL
datazen-3.2.3.dist-info/entry_points.txt
datazen-3.2.3.dist-info/top_level.txt
datazen-3.2.3.dist-info/RECORD
