Metadata-Version: 2.4
Name: datazen
Version: 3.2.3
Summary: Compile and render schema-validated configuration data.
Home-page: https://github.com/libre-embedded/datazen
Author: Libre Embedded
Author-email: Libre Embedded <vaughn@libre-embedded.com>
Maintainer-email: Libre Embedded <vaughn@libre-embedded.com>
License-Expression: MIT
Classifier: Programming Language :: Python :: 3.12
Classifier: Programming Language :: Python :: 3.13
Classifier: Operating System :: Microsoft :: Windows
Classifier: Operating System :: MacOS
Classifier: Operating System :: POSIX :: Linux
Classifier: Operating System :: Unix
Classifier: Development Status :: 5 - Production/Stable
Requires-Python: >=3.12
License-File: LICENSE
Requires-Dist: GitPython
Requires-Dist: cerberus
Requires-Dist: Jinja2
Requires-Dist: vcorelib>=1.2.3
Provides-Extra: test
Requires-Dist: pylint; extra == "test"
Requires-Dist: flake8; extra == "test"
Requires-Dist: black; extra == "test"
Requires-Dist: ruff; extra == "test"
Requires-Dist: mypy; extra == "test"
Requires-Dist: isort; extra == "test"
Requires-Dist: yamllint; extra == "test"
Requires-Dist: yambs; extra == "test"
Requires-Dist: vmklib>=2.0.3; extra == "test"
Requires-Dist: sphinx; extra == "test"
Requires-Dist: sphinx-book-theme; extra == "test"
Requires-Dist: setuptools-wrapper; extra == "test"
Requires-Dist: pytest; extra == "test"
Dynamic: author
Dynamic: home-page
Dynamic: license-file
Dynamic: requires-dist
Dynamic: requires-python
